scine_readuct/__init__.py
scine_readuct/libcore.so
scine_readuct/libreaduct.so
scine_readuct/libutilsos.so
scine_readuct/scine_readuct.cpython-38-x86_64-linux-gnu.so
scine_readuct.libs/libboost_atomic-00e6ede8.so.1.78.0
scine_readuct.libs/libboost_filesystem-e9e1d9ac.so.1.78.0
scine_readuct.libs/libboost_system-c0fa27da.so.1.78.0
scine_readuct.libs/libcore-6a155538.so
scine_readuct.libs/libgomp-e985bcbb.so.1.0.0
scine_readuct.libs/libreaduct-4549111a.so
scine_readuct.libs/libutilsos-1a1c26a4.so
scine_readuct-6.1.0.dist-info/METADATA
scine_readuct-6.1.0.dist-info/WHEEL
scine_readuct-6.1.0.dist-info/top_level.txt
scine_readuct-6.1.0.dist-info/RECORD
